swisseph.cpython-313-x86_64-linux-gnu.so
pysweph-2.10.3.3.dist-info/METADATA
pysweph-2.10.3.3.dist-info/WHEEL
pysweph-2.10.3.3.dist-info/top_level.txt
pysweph-2.10.3.3.dist-info/RECORD
pysweph-2.10.3.3.dist-info/licenses/LICENSE.txt
