Metadata-Version: 2.4
Name: pysweph
Version: 2.10.3.3
Summary: Community fork of Pyswisseph, a Python extension to the Swiss Ephemeris
Author-email: Stanislas Marquis <stan@astrorigin.com>
Maintainer-email: Kathryn de la Rosa <hello@sailorfe.dev>
License-Expression: AGPL-3.0-or-later
Project-URL: Homepage, https://sailorfe.github.io/pysweph
Project-URL: Documentation, https://sailorfe.github.io/pysweph
Project-URL: Repository, https://github.com/sailorfe/pysweph
Project-URL: Issues, https://github.com/sailorfe/pysweph/issues
Project-URL: Original Project, https://github.com/astrorigin/pyswisseph
Keywords: astrology,ephemeris,swisseph,astronomy
Classifier: Development Status :: 4 - Beta
Classifier: Intended Audience :: Developers
Classifier: Intended Audience :: Religion
Classifier: Programming Language :: C
Classifier: Programming Language :: Python :: 3
Classifier: Programming Language :: Python :: 3.8
Classifier: Programming Language :: Python :: 3.9
Classifier: Programming Language :: Python :: 3.10
Classifier: Programming Language :: Python :: 3.11
Classifier: Programming Language :: Python :: 3.12
Classifier: Programming Language :: Python :: 3.13
Classifier: Topic :: Religion
Classifier: Topic :: Scientific/Engineering :: Astronomy
Classifier: Topic :: Software Development :: Libraries :: Python Modules
Requires-Python: >=3.8
License-File: LICENSE.txt
Dynamic: license-file
